.gitignore
.travis.yml
LICENSE
MANIFEST.in
Makefile
README.rst
requirements.txt
setup.py
django_payline.egg-info/PKG-INFO
django_payline.egg-info/SOURCES.txt
django_payline.egg-info/dependency_links.txt
django_payline.egg-info/not-zip-safe
django_payline.egg-info/top_level.txt
docs/Makefile
docs/conf.py
docs/index.rst
payline/DirectPaymentAPI.wsdl
payline/DirectPaymentAPI_prod.wsdl
payline/__init__.py
payline/forms.py
payline/models.py
payline/processor.py
payline/settings.py
payline/test_settings.py
payline/tests.py
payline/views.py
payline/locale/en/LC_MESSAGES/django.po
payline/locale/fr/LC_MESSAGES/django.mo
payline/locale/fr/LC_MESSAGES/django.po
payline/templates/payline/wallet_detail.html
payline/templates/payline/wallet_detail_partial.html
payline/templates/payline/wallet_form.html