Metadata-Version: 1.1
Name: django-payline
Version: 0.10
Summary: Payments using Payline
Home-page: https://github.com/magopian/django-payline
Author: Mathieu Agopian
Author-email: mathieu.agopian@gmail.com
License: BSD licence, see LICENSE file
Platform: UNKNOWN
Classifier: Development Status :: 4 - Beta
Classifier: Environment :: Web Environment
Classifier: Framework :: Django
Classifier: Intended Audience :: Developers
Classifier: License :: OSI Approved :: BSD License
Classifier: Natural Language :: English
Classifier: Programming Language :: Python
